[
  {
    "model": "auth.user",
    "pk": 1,
    "fields": {
      "password": "pbkdf2_sha256$180000$GZKHpeZSQAQi$wAWLGldJBUyJZJqHEy7lrlMlp+8iePWdmrzQ/hNTXLE=",
      "last_login": "2020-01-24T11:41:35.361Z",
      "is_superuser": true,
      "username": "admin",
      "first_name": "",
      "last_name": "",
      "email": "admin@example.com",
      "is_staff": true,
      "is_active": true,
      "date_joined": "2020-01-24T11:41:04.245Z",
      "groups": [],
      "user_permissions": []
    }
  },
  {
    "model": "transactions.category",
    "pk": 1,
    "fields": {
      "name": "jedzenie"
    }
  },
  {
    "model": "transactions.category",
    "pk": 2,
    "fields": {
      "name": "nauka"
    }
  },
  {
    "model": "transactions.wallet",
    "pk": 1,
    "fields": {
      "name": "Default",
      "balance": "0.00"
    }
  },
  {
    "model": "transactions.transaction",
    "pk": 1,
    "fields": {
      "wallet": 1,
      "category": 1,
      "title": "p\u0105czki",
      "amount": "2.50",
      "type": "exp",
      "created": "2020-01-24T11:42:13Z"
    }
  },
  {
    "model": "transactions.transaction",
    "pk": 2,
    "fields": {
      "wallet": 1,
      "category": 1,
      "title": "pizza",
      "amount": "100.00",
      "type": "inc",
      "created": "2020-01-24T11:42:31Z"
    }
  },
  {
    "model": "transactions.transaction",
    "pk": 3,
    "fields": {
      "wallet": 1,
      "category": 2,
      "title": "ksi\u0105\u017cki",
      "amount": "150.99",
      "type": "exp",
      "created": "2020-01-24T11:44:11Z"
    }
  }
]